galaxy/report/__init__.py
galaxy/report/config/__init__.py
galaxy/report/config/generator.py
galaxy/report/config/parser.py
galaxy/report/csv/__init__.py
galaxy/report/csv/generator.py
galaxy/report/csv/parser.py
galaxy/report/factory.py
galaxy/report/json/__init__.py
galaxy/report/json/generator.py
galaxy/report/json/parser.py
galaxy/report/pdf/__init__.py
galaxy/report/pdf/generator.py
galaxy/report/pdf/parser.py
galaxy/report/report.py
galaxy/report/toml/__init__.py
galaxy/report/toml/generator.py
galaxy/report/toml/parser.py
galaxy/report/txt/__init__.py
galaxy/report/txt/generator.py
galaxy/report/txt/parser.py
galaxy/report/utils.py
galaxy/report/xls/__init__.py
galaxy/report/xls/generator.py
galaxy/report/xls/parser.py
galaxy/report/xml/__init__.py
galaxy/report/xml/generator.py
galaxy/report/xml/parser.py
galaxy/report/yaml/__init__.py
galaxy/report/yaml/generator.py
galaxy/report/yaml/parser.py
galaxy_py_report-0.0.8.dist-info/AUTHORS
galaxy_py_report-0.0.8.dist-info/COPYING.md
galaxy_py_report-0.0.8.dist-info/LICENSE.txt
galaxy_py_report-0.0.8.dist-info/METADATA
galaxy_py_report-0.0.8.dist-info/WHEEL
galaxy_py_report-0.0.8.dist-info/RECORD
