Metadata-Version: 2.3
Name: galaxy-py-report
Version: 0.0.8
Summary: Python Reporting for the Galaxy Project
License: Apache-2.0
Keywords: galaxy,galaxy-report
Author: Bastien Saltel
Author-email: bastien.saltel@gmail.com
Maintainer: Bastien Saltel
Maintainer-email: bastien.saltel@gmail.com
Requires-Python: >=3.10,<4.0
Classifier: Development Status :: 3 - Alpha
Classifier: Programming Language :: Python :: 3
Classifier: Operating System :: OS Independent
Requires-Dist: aiocsv
Requires-Dist: aiofile
Requires-Dist: aioshutil
Requires-Dist: galaxy-py-data
Requires-Dist: galaxy-py-service
Requires-Dist: galaxy-py-utils
Requires-Dist: openpyxl
Requires-Dist: pymupdf
Requires-Dist: pypdf
Requires-Dist: pypdf3
Requires-Dist: pyyaml
Requires-Dist: tabula
Requires-Dist: xlsxwriter
Project-URL: Changelog, https://github.com/bsaltel/galaxy-py-report/blob/main/CHANGELOG.md
Project-URL: Documentation, https://github.com/bsaltel/galaxy-py-report
Project-URL: Homepage, https://github.com/bsaltel/galaxy-py-report
Project-URL: Issues, https://github.com/bsaltel/galaxy-py-report/issues
Project-URL: Repository, https://github.com/bsaltel/galaxy-py-report.git
